soundscrape/__init__.py
soundscrape/soundscrape.py
soundscrape-0.31.0.dist-info/LICENSE
soundscrape-0.31.0.dist-info/METADATA
soundscrape-0.31.0.dist-info/WHEEL
soundscrape-0.31.0.dist-info/entry_points.txt
soundscrape-0.31.0.dist-info/pbr.json
soundscrape-0.31.0.dist-info/top_level.txt
soundscrape-0.31.0.dist-info/RECORD
