Metadata-Version: 2.1
Name: soundscrape
Version: 0.31.0
Summary: Scrape an artist from SoundCloud
Home-page: https://github.com/Miserlou/SoundScrape
Author: Rich Jones
Author-email: rich@openwatch.net
License: MIT License
Platform: UNKNOWN
Classifier: Environment :: Console
Classifier: License :: OSI Approved :: Apache Software License
Classifier: Operating System :: OS Independent
Classifier: Programming Language :: Python
Classifier: Programming Language :: Python :: 3.4
Classifier: Programming Language :: Python :: 3.5
Classifier: Programming Language :: Python :: 3.7
Classifier: Programming Language :: Python :: 3.8
Classifier: Programming Language :: Python :: 3.9
Classifier: Topic :: Internet :: WWW/HTTP
Classifier: Topic :: Internet :: WWW/HTTP :: Dynamic Content
Requires-Dist: args (>=0.1.0)
Requires-Dist: clint (>=0.3.2)
Requires-Dist: demjson (>=2.2.2)
Requires-Dist: fudge (>=1.0.3)
Requires-Dist: nose (>=1.3.7)
Requires-Dist: requests[security] (>=2.9.0)
Requires-Dist: setuptools (>=18.0.0)
Requires-Dist: simplejson (>=3.3.1)
Requires-Dist: soundcloud (>=0.4.1)
Requires-Dist: wheel (>=0.24.0)
Requires-Dist: mutagen (>=1.31.0)
Requires-Dist: wsgiref (>=0.1.2) ; python_version < "3.0"
